bge_utils/__init__.py
bge_utils/convert_utils.py
bge_utils/datetime_utils.py
bge_utils/excel_utils.py
bge_utils/file_utils.py
bge_utils/math_utils.py
bge_utils/py_utils.py
bge_utils-1.2.dist-info/METADATA
bge_utils-1.2.dist-info/WHEEL
bge_utils-1.2.dist-info/licenses/LICENSE
bge_utils-1.2.dist-info/RECORD
