Metadata-Version: 2.4
Name: bge_utils
Version: 1.2
Summary: A package with commonly used pieces of code.
Author: Bacchus
License-Expression: MIT
License-File: LICENSE
Classifier: Operating System :: OS Independent
Classifier: Programming Language :: Python :: 3
Requires-Python: >=3.9
Requires-Dist: pillow
Requires-Dist: requests
Provides-Extra: excel
Requires-Dist: excel2img; extra == 'excel'
